itc2kc.py
itc2kc-0.1.1.dist-info/METADATA
itc2kc-0.1.1.dist-info/WHEEL
itc2kc-0.1.1.dist-info/entry_points.txt
itc2kc-0.1.1.dist-info/licenses/LICENSE
itc2kc-0.1.1.dist-info/RECORD
