Metadata-Version: 2.4
Name: itc2kc
Version: 0.1.1
Summary: A converter for iTerm2 to kitty themes
Project-URL: Homepage, https://github.com/ejohnso49/itc2kc
Project-URL: Repository, https://github.com/ejohnso49/itc2kc
Project-URL: Changelog, https://github.com/ejohnso49/itc2kc/blob/master/CHANGELOG.md
Project-URL: Issues, https://github.com/ejohnso49/itc2kc/issues
Author-email: Eric Johnson <eric.j.johnson22@gmail.com>
License-Expression: Apache-2.0
License-File: LICENSE
Classifier: Environment :: Console
Classifier: Intended Audience :: Developers
Classifier: License :: OSI Approved :: Apache Software License
Classifier: Topic :: Terminals :: Terminal Emulators/X Terminals
Requires-Python: >=3.12
Requires-Dist: lxml>=5.3.1
